SBGeom/Optimisers.py
SBGeom/Coils.py
SBGeom/__init__.py
SBGeom/Flux_Surfaces.py
SBGeom/Optimise_Blanket_Direct.py
SBGeom/SBGeom_cpp.pypy37-pp73-x86_64-linux-gnu.so
SBGeom/Optimise_Blanket.py
SBGeom/HB_Boundary_representation.py
SBGeom/helper_functions_cpp.py
sbgeom.libs/libgomp-a34b3233.so.1.0.0
sbgeom-0.1.dist-info/RECORD
sbgeom-0.1.dist-info/METADATA
sbgeom-0.1.dist-info/WHEEL
sbgeom-0.1.dist-info/licenses/LICENSE.txt
