Metadata-Version: 2.1
Name: SBGeom
Version: 0.1
Summary: Python package for creating stellarator geometry
Author-Email: Timo Bogaarts <t.j.bogaarts@tue.nl>
Requires-Dist: numpy
Requires-Dist: meshio
Requires-Dist: h5py
Requires-Dist: jax
Requires-Dist: jaxlib
